eks_cli/__init__.py
eks_cli/checker.py
eks_cli/cli.py
eks_cli/security.py
eks_cli/checks/__init__.py
eks_cli/checks/addons.py
eks_cli/checks/amis.py
eks_cli/checks/autoscaling.py
eks_cli/checks/base.py
eks_cli/checks/iam.py
eks_cli/checks/identity.py
eks_cli/checks/instances.py
eks_cli/checks/loadbalancers.py
eks_cli/checks/ssh.py
eks_cli/checks/userdata.py
eks_cli/checks/version.py
eks_cli/checks/windows.py
preflight_check_cli_for_eks_auto_mode-0.1.1.dist-info/licenses/LICENSE
preflight_check_cli_for_eks_auto_mode-0.1.1.dist-info/licenses/NOTICE
preflight_check_cli_for_eks_auto_mode-0.1.1.dist-info/METADATA
preflight_check_cli_for_eks_auto_mode-0.1.1.dist-info/WHEEL
preflight_check_cli_for_eks_auto_mode-0.1.1.dist-info/entry_points.txt
preflight_check_cli_for_eks_auto_mode-0.1.1.dist-info/top_level.txt
preflight_check_cli_for_eks_auto_mode-0.1.1.dist-info/RECORD
