Metadata-Version: 2.4
Name: preflight-check-cli-for-eks-auto-mode
Version: 0.1.1
Summary: Preflight Check CLI for EKS Auto Mode - assess cluster readiness for migration
Author: EKS Auto Mode Preflight Contributors
License: Apache-2.0
Project-URL: Homepage, https://github.com/rleekin/eks-automode-preflight-checker-cli
Project-URL: Repository, https://github.com/rleekin/eks-automode-preflight-checker-cli
Project-URL: PyPI, https://pypi.org/project/preflight-check-cli-for-eks-auto-mode/
Classifier: Development Status :: 4 - Beta
Classifier: Intended Audience :: System Administrators
Classifier: License :: OSI Approved :: Apache Software License
Classifier: Operating System :: OS Independent
Classifier: Programming Language :: Python :: 3
Classifier: Programming Language :: Python :: 3.7
Classifier: Programming Language :: Python :: 3.8
Classifier: Programming Language :: Python :: 3.9
Classifier: Programming Language :: Python :: 3.10
Classifier: Programming Language :: Python :: 3.11
Classifier: Topic :: System :: Systems Administration
Classifier: Topic :: Utilities
Requires-Python: >=3.7
License-File: LICENSE
License-File: NOTICE
Requires-Dist: click
Requires-Dist: boto3
Requires-Dist: tabulate
Requires-Dist: pyyaml
Requires-Dist: packaging
Dynamic: license-file
